CHANGES.txt
MANIFEST.in
README.txt
setup.py
awsbuilder/__init__.py
awsbuilder/awsbuilder
awsbuilder.egg-info/PKG-INFO
awsbuilder.egg-info/SOURCES.txt
awsbuilder.egg-info/dependency_links.txt
awsbuilder.egg-info/requires.txt
awsbuilder.egg-info/top_level.txt