Metadata-Version: 1.1
Name: awsbuilder
Version: 0.0.3
Summary: Command line tools top create AWS objects based on a config file
Home-page: https://github.com/ministryofjustice/awsbuilder
Author: Stuart Munro
Author-email: stuart.munro@digital.justice.gov.uk
License: MIT
Platform: Posix; MacOS X
Classifier: Intended Audience :: Developers
Classifier: License :: OSI Approved :: MIT License
Classifier: Topic :: Internet
